setup.py
mockredis/__init__.py
mockredis/clock.py
mockredis/exceptions.py
mockredis/lock.py
mockredis/pipeline.py
mockredis/redis.py
mockredis/script.py
mockredis/sortedset.py
mockredispy.egg-info/PKG-INFO
mockredispy.egg-info/SOURCES.txt
mockredispy.egg-info/dependency_links.txt
mockredispy.egg-info/entry_points.txt
mockredispy.egg-info/requires.txt
mockredispy.egg-info/top_level.txt