Metadata-Version: 1.0
Name: mockredispy
Version: 2.8.0.4
Summary: Mock for redis-py
Home-page: http://www.github.com/locationlabs/mockredis
Author: UNKNOWN
Author-email: UNKNOWN
License: Apache2
Platform: UNKNOWN
